{
  "US": {
    "name": "アメリカ",
    "flag": "🇺🇸",
    "score": 92,
    "trends": [
      {
        "word": "トランプ",
        "count": 50004,
        "cat": "tech",
        "trend": "up",
        "rank": 1,
        "originalEng": "trump"
      },
      {
        "word": "launches",
        "count": 46830,
        "cat": "social",
        "trend": "down",
        "rank": 2,
        "originalEng": "launches"
      },
      {
        "word": "を起動します",
        "count": 43731,
        "cat": "econ",
        "trend": "down",
        "rank": 3,
        "originalEng": "text"
      },
      {
        "word": "テキスト",
        "count": 38550,
        "cat": "tech",
        "trend": "up",
        "rank": 4,
        "originalEng": "peace"
      },
      {
        "word": "平和",
        "count": 35536,
        "cat": "geo",
        "trend": "up",
        "rank": 5,
        "originalEng": "deal"
      },
      {
        "word": "取引",
        "count": 31514,
        "cat": "tech",
        "trend": "up",
        "rank": 6,
        "originalEng": "georgia"
      },
      {
        "word": "ジョージア",
        "count": 26529,
        "cat": "geo",
        "trend": "up",
        "rank": 7,
        "originalEng": "opening"
      },
      {
        "word": "オープニング",
        "count": 22408,
        "cat": "tech",
        "trend": "up",
        "rank": 8,
        "originalEng": "africa"
      },
      {
        "word": "アフリカ",
        "count": 19228,
        "cat": "social",
        "trend": "down",
        "rank": 9,
        "originalEng": "meeting"
      },
      {
        "word": "会議",
        "count": 14451,
        "cat": "econ",
        "trend": "down",
        "rank": 10,
        "originalEng": "fed"
      }
    ]
  },
  "JP": {
    "name": "日本",
    "flag": "🇯🇵",
    "score": 78,
    "trends": [
      {
        "word": "給餌",
        "count": 51417,
        "cat": "tech",
        "trend": "up",
        "rank": 1,
        "originalEng": "yen"
      },
      {
        "word": "円",
        "count": 47744,
        "cat": "tech",
        "trend": "up",
        "rank": 2,
        "originalEng": "june"
      },
      {
        "word": "6月",
        "count": 42181,
        "cat": "tech",
        "trend": "up",
        "rank": 3,
        "originalEng": "results"
      },
      {
        "word": "結果",
        "count": 38923,
        "cat": "social",
        "trend": "down",
        "rank": 4,
        "originalEng": "off"
      },
      {
        "word": "オフ",
        "count": 35551,
        "cat": "social",
        "trend": "down",
        "rank": 5,
        "originalEng": "sale"
      },
      {
        "word": "セール",
        "count": 31892,
        "cat": "tech",
        "trend": "up",
        "rank": 6,
        "originalEng": "cup"
      },
      {
        "word": "カップ",
        "count": 27592,
        "cat": "econ",
        "trend": "down",
        "rank": 7,
        "originalEng": "strait"
      },
      {
        "word": "海峡",
        "count": 23028,
        "cat": "econ",
        "trend": "down",
        "rank": 8,
        "originalEng": "hormuz"
      },
      {
        "word": "ホルムズ",
        "count": 19171,
        "cat": "geo",
        "trend": "up",
        "rank": 9,
        "originalEng": "weather"
      },
      {
        "word": "天気",
        "count": 15890,
        "cat": "social",
        "trend": "down",
        "rank": 10,
        "originalEng": "tomorrow"
      }
    ]
  },
  "GB": {
    "name": "イギリス",
    "flag": "🇬🇧",
    "score": 61,
    "trends": [
      {
        "word": "明日",
        "count": 51002,
        "cat": "social",
        "trend": "down",
        "rank": 1,
        "originalEng": "england"
      },
      {
        "word": "セール",
        "count": 47362,
        "cat": "tech",
        "trend": "up",
        "rank": 2,
        "originalEng": "cup"
      },
      {
        "word": "トランプ",
        "count": 43165,
        "cat": "tech",
        "trend": "up",
        "rank": 3,
        "originalEng": "trump"
      },
      {
        "word": "イングランド",
        "count": 38294,
        "cat": "geo",
        "trend": "up",
        "rank": 4,
        "originalEng": "starmer"
      },
      {
        "word": "スターマー",
        "count": 35425,
        "cat": "geo",
        "trend": "up",
        "rank": 5,
        "originalEng": "holds"
      },
      {
        "word": "job",
        "count": 31047,
        "cat": "econ",
        "trend": "down",
        "rank": 6,
        "originalEng": "job"
      },
      {
        "word": "平和",
        "count": 27186,
        "cat": "geo",
        "trend": "up",
        "rank": 7,
        "originalEng": "deal"
      },
      {
        "word": "が成立します仕事",
        "count": 23194,
        "cat": "econ",
        "trend": "down",
        "rank": 8,
        "originalEng": "votes"
      },
      {
        "word": "投票",
        "count": 18727,
        "cat": "econ",
        "trend": "down",
        "rank": 9,
        "originalEng": "ill"
      },
      {
        "word": "病気",
        "count": 14695,
        "cat": "tech",
        "trend": "up",
        "rank": 10,
        "originalEng": "iran"
      }
    ]
  },
  "DE": {
    "name": "ドイツ",
    "flag": "🇩🇪",
    "score": 67,
    "trends": [
      {
        "word": "イラン",
        "count": 50686,
        "cat": "tech",
        "trend": "up",
        "rank": 1,
        "originalEng": "agreement"
      },
      {
        "word": "病気",
        "count": 47756,
        "cat": "tech",
        "trend": "up",
        "rank": 2,
        "originalEng": "iran"
      },
      {
        "word": "同意",
        "count": 43591,
        "cat": "social",
        "trend": "down",
        "rank": 3,
        "originalEng": "usa"
      },
      {
        "word": "アメリカ",
        "count": 39908,
        "cat": "tech",
        "trend": "up",
        "rank": 4,
        "originalEng": "five"
      },
      {
        "word": "レート",
        "count": 35108,
        "cat": "geo",
        "trend": "up",
        "rank": 5,
        "originalEng": "rate"
      },
      {
        "word": "いつ",
        "count": 31912,
        "cat": "tech",
        "trend": "up",
        "rank": 6,
        "originalEng": "when"
      },
      {
        "word": "熱",
        "count": 27408,
        "cat": "geo",
        "trend": "up",
        "rank": 7,
        "originalEng": "heat"
      },
      {
        "word": "車",
        "count": 23721,
        "cat": "geo",
        "trend": "up",
        "rank": 8,
        "originalEng": "car"
      },
      {
        "word": "ドイツ",
        "count": 19316,
        "cat": "econ",
        "trend": "down",
        "rank": 9,
        "originalEng": "germany"
      },
      {
        "word": "開始",
        "count": 14307,
        "cat": "tech",
        "trend": "up",
        "rank": 10,
        "originalEng": "start"
      }
    ]
  },
  "IN": {
    "name": "インド",
    "flag": "🇮🇳",
    "score": 82,
    "trends": [
      {
        "word": "病気",
        "count": 51544,
        "cat": "tech",
        "trend": "up",
        "rank": 1,
        "originalEng": "iran"
      },
      {
        "word": "トランプ",
        "count": 47134,
        "cat": "tech",
        "trend": "up",
        "rank": 2,
        "originalEng": "trump"
      },
      {
        "word": "平和",
        "count": 43178,
        "cat": "geo",
        "trend": "up",
        "rank": 3,
        "originalEng": "deal"
      },
      {
        "word": "ニート",
        "count": 38765,
        "cat": "tech",
        "trend": "up",
        "rank": 4,
        "originalEng": "neet"
      },
      {
        "word": "インド",
        "count": 35075,
        "cat": "social",
        "trend": "down",
        "rank": 5,
        "originalEng": "india"
      },
      {
        "word": "テキスト",
        "count": 30690,
        "cat": "tech",
        "trend": "up",
        "rank": 6,
        "originalEng": "peace"
      },
      {
        "word": "セール",
        "count": 27007,
        "cat": "tech",
        "trend": "up",
        "rank": 7,
        "originalEng": "cup"
      },
      {
        "word": "勉強",
        "count": 22519,
        "cat": "econ",
        "trend": "down",
        "rank": 8,
        "originalEng": "study"
      },
      {
        "word": "インド",
        "count": 19461,
        "cat": "geo",
        "trend": "up",
        "rank": 9,
        "originalEng": "indias"
      },
      {
        "word": "モディ",
        "count": 14627,
        "cat": "social",
        "trend": "down",
        "rank": 10,
        "originalEng": "modi"
      }
    ]
  },
  "FR": {
    "name": "フランス",
    "flag": "🇫🇷",
    "score": 59,
    "trends": [
      {
        "word": "戦争",
        "count": 51592,
        "cat": "geo",
        "trend": "up",
        "rank": 1,
        "originalEng": "war"
      },
      {
        "word": "団結",
        "count": 47069,
        "cat": "econ",
        "trend": "down",
        "rank": 2,
        "originalEng": "united"
      },
      {
        "word": "熱",
        "count": 43429,
        "cat": "geo",
        "trend": "up",
        "rank": 3,
        "originalEng": "heat"
      },
      {
        "word": "欲しい",
        "count": 38278,
        "cat": "social",
        "trend": "down",
        "rank": 4,
        "originalEng": "wants"
      },
      {
        "word": "not",
        "count": 35068,
        "cat": "social",
        "trend": "down",
        "rank": 5,
        "originalEng": "not"
      },
      {
        "word": "病気",
        "count": 31666,
        "cat": "tech",
        "trend": "up",
        "rank": 6,
        "originalEng": "iran"
      },
      {
        "word": "ではありません",
        "count": 27834,
        "cat": "tech",
        "trend": "up",
        "rank": 7,
        "originalEng": "states"
      },
      {
        "word": "状態",
        "count": 23519,
        "cat": "econ",
        "trend": "down",
        "rank": 8,
        "originalEng": "wave"
      },
      {
        "word": "波",
        "count": 18069,
        "cat": "geo",
        "trend": "up",
        "rank": 9,
        "originalEng": "change"
      },
      {
        "word": "変更",
        "count": 15642,
        "cat": "geo",
        "trend": "up",
        "rank": 10,
        "originalEng": "putin"
      }
    ]
  },
  "AU": {
    "name": "オーストラリア",
    "flag": "🇦🇺",
    "score": 55,
    "trends": [
      {
        "word": "プーチン",
        "count": 51731,
        "cat": "social",
        "trend": "down",
        "rank": 1,
        "originalEng": "home"
      },
      {
        "word": "ホーム",
        "count": 47541,
        "cat": "social",
        "trend": "down",
        "rank": 2,
        "originalEng": "ceasefire"
      },
      {
        "word": "病気",
        "count": 42276,
        "cat": "tech",
        "trend": "up",
        "rank": 3,
        "originalEng": "iran"
      },
      {
        "word": "停戦",
        "count": 38046,
        "cat": "geo",
        "trend": "up",
        "rank": 4,
        "originalEng": "its"
      },
      {
        "word": "それ",
        "count": 35348,
        "cat": "tech",
        "trend": "up",
        "rank": 5,
        "originalEng": "drastic"
      },
      {
        "word": "劇的",
        "count": 31292,
        "cat": "econ",
        "trend": "down",
        "rank": 6,
        "originalEng": "confirms"
      },
      {
        "word": "確認します",
        "count": 26094,
        "cat": "social",
        "trend": "down",
        "rank": 7,
        "originalEng": "back"
      },
      {
        "word": "戻る",
        "count": 22328,
        "cat": "econ",
        "trend": "down",
        "rank": 8,
        "originalEng": "rba"
      },
      {
        "word": "rba",
        "count": 19830,
        "cat": "geo",
        "trend": "up",
        "rank": 9,
        "originalEng": "gold"
      },
      {
        "word": "ゴールド",
        "count": 14346,
        "cat": "tech",
        "trend": "up",
        "rank": 10,
        "originalEng": "leaders"
      }
    ]
  },
  "KR": {
    "name": "韓国",
    "flag": "🇰🇷",
    "score": 74,
    "trends": [
      {
        "word": "リーダー",
        "count": 50387,
        "cat": "social",
        "trend": "down",
        "rank": 1,
        "originalEng": "election"
      },
      {
        "word": "選挙",
        "count": 46177,
        "cat": "tech",
        "trend": "up",
        "rank": 2,
        "originalEng": "national"
      },
      {
        "word": "社長",
        "count": 43439,
        "cat": "geo",
        "trend": "up",
        "rank": 3,
        "originalEng": "president"
      },
      {
        "word": "リー",
        "count": 39522,
        "cat": "geo",
        "trend": "up",
        "rank": 4,
        "originalEng": "lee"
      },
      {
        "word": "パワー",
        "count": 35082,
        "cat": "econ",
        "trend": "down",
        "rank": 5,
        "originalEng": "power"
      },
      {
        "word": "韓国",
        "count": 30369,
        "cat": "tech",
        "trend": "up",
        "rank": 6,
        "originalEng": "korea"
      },
      {
        "word": "becomes",
        "count": 26209,
        "cat": "geo",
        "trend": "up",
        "rank": 7,
        "originalEng": "becomes"
      },
      {
        "word": "トランプ",
        "count": 23453,
        "cat": "tech",
        "trend": "up",
        "rank": 8,
        "originalEng": "trump"
      },
      {
        "word": "になりますもう",
        "count": 19310,
        "cat": "social",
        "trend": "down",
        "rank": 9,
        "originalEng": "mou"
      },
      {
        "word": "病気",
        "count": 14342,
        "cat": "tech",
        "trend": "up",
        "rank": 10,
        "originalEng": "iran"
      }
    ]
  },
  "BR": {
    "name": "ブラジル",
    "flag": "🇧🇷",
    "score": 52,
    "trends": [
      {
        "word": "ルラ",
        "count": 50766,
        "cat": "tech",
        "trend": "up",
        "rank": 1,
        "originalEng": "lula"
      },
      {
        "word": "トランプ",
        "count": 47205,
        "cat": "tech",
        "trend": "up",
        "rank": 2,
        "originalEng": "trump"
      },
      {
        "word": "アフリカ",
        "count": 42417,
        "cat": "social",
        "trend": "down",
        "rank": 3,
        "originalEng": "meeting"
      },
      {
        "word": "ブラジル",
        "count": 38254,
        "cat": "geo",
        "trend": "up",
        "rank": 4,
        "originalEng": "brazil"
      },
      {
        "word": "creates",
        "count": 34700,
        "cat": "social",
        "trend": "down",
        "rank": 5,
        "originalEng": "creates"
      },
      {
        "word": "を作成します女優",
        "count": 30115,
        "cat": "social",
        "trend": "down",
        "rank": 6,
        "originalEng": "actress"
      },
      {
        "word": "ボルソナロス",
        "count": 26143,
        "cat": "geo",
        "trend": "up",
        "rank": 7,
        "originalEng": "bolsonaros"
      },
      {
        "word": "see",
        "count": 23477,
        "cat": "social",
        "trend": "down",
        "rank": 8,
        "originalEng": "see"
      },
      {
        "word": "セール",
        "count": 18877,
        "cat": "tech",
        "trend": "up",
        "rank": 9,
        "originalEng": "cup"
      },
      {
        "word": "を参照してください。ボルカロ",
        "count": 14541,
        "cat": "geo",
        "trend": "up",
        "rank": 10,
        "originalEng": "vorcaro"
      }
    ]
  },
  "CA": {
    "name": "カナダ",
    "flag": "🇨🇦",
    "score": 58,
    "trends": [
      {
        "word": "トランプ",
        "count": 51800,
        "cat": "tech",
        "trend": "up",
        "rank": 1,
        "originalEng": "trump"
      },
      {
        "word": "カーニー",
        "count": 46195,
        "cat": "tech",
        "trend": "up",
        "rank": 2,
        "originalEng": "carney"
      },
      {
        "word": "充電済み",
        "count": 42659,
        "cat": "geo",
        "trend": "up",
        "rank": 3,
        "originalEng": "charged"
      },
      {
        "word": "ドナルド",
        "count": 38513,
        "cat": "tech",
        "trend": "up",
        "rank": 4,
        "originalEng": "donald"
      },
      {
        "word": "問題",
        "count": 35946,
        "cat": "tech",
        "trend": "up",
        "rank": 5,
        "originalEng": "issues"
      },
      {
        "word": "水",
        "count": 30060,
        "cat": "social",
        "trend": "down",
        "rank": 6,
        "originalEng": "water"
      },
      {
        "word": "車両",
        "count": 27631,
        "cat": "geo",
        "trend": "up",
        "rank": 7,
        "originalEng": "vehicle"
      },
      {
        "word": "カナダ",
        "count": 22326,
        "cat": "econ",
        "trend": "down",
        "rank": 8,
        "originalEng": "canadas"
      },
      {
        "word": "スターマー",
        "count": 19394,
        "cat": "geo",
        "trend": "up",
        "rank": 9,
        "originalEng": "holds"
      },
      {
        "word": "ダウン",
        "count": 14800,
        "cat": "tech",
        "trend": "up",
        "rank": 10,
        "originalEng": "down"
      }
    ]
  },
  "RU": {
    "name": "ロシア",
    "flag": "🇷🇺",
    "score": 80,
    "trends": [
      {
        "word": "ウクライナ語",
        "count": 50169,
        "cat": "geo",
        "trend": "up",
        "rank": 1,
        "originalEng": "ukrainian"
      },
      {
        "word": "武装",
        "count": 47807,
        "cat": "social",
        "trend": "down",
        "rank": 2,
        "originalEng": "armed"
      },
      {
        "word": "力",
        "count": 43145,
        "cat": "geo",
        "trend": "up",
        "rank": 3,
        "originalEng": "forces"
      },
      {
        "word": "ロシア語",
        "count": 38205,
        "cat": "social",
        "trend": "down",
        "rank": 4,
        "originalEng": "russian"
      },
      {
        "word": "オイル",
        "count": 34585,
        "cat": "tech",
        "trend": "up",
        "rank": 5,
        "originalEng": "oil"
      },
      {
        "word": "停戦",
        "count": 30587,
        "cat": "geo",
        "trend": "up",
        "rank": 6,
        "originalEng": "its"
      },
      {
        "word": "明らかになった",
        "count": 26676,
        "cat": "geo",
        "trend": "up",
        "rank": 7,
        "originalEng": "revealed"
      },
      {
        "word": "頂上",
        "count": 23710,
        "cat": "social",
        "trend": "down",
        "rank": 8,
        "originalEng": "summit"
      },
      {
        "word": "選手",
        "count": 18186,
        "cat": "tech",
        "trend": "up",
        "rank": 9,
        "originalEng": "players"
      },
      {
        "word": "ドローン",
        "count": 15578,
        "cat": "econ",
        "trend": "down",
        "rank": 10,
        "originalEng": "drones"
      }
    ]
  },
  "CN": {
    "name": "中国",
    "flag": "🇨🇳",
    "score": 85,
    "trends": [
      {
        "word": "ホン",
        "count": 51319,
        "cat": "geo",
        "trend": "up",
        "rank": 1,
        "originalEng": "hong"
      },
      {
        "word": "コン",
        "count": 46642,
        "cat": "econ",
        "trend": "down",
        "rank": 2,
        "originalEng": "kong"
      },
      {
        "word": "セール",
        "count": 42091,
        "cat": "tech",
        "trend": "up",
        "rank": 3,
        "originalEng": "cup"
      },
      {
        "word": "重い",
        "count": 39676,
        "cat": "social",
        "trend": "down",
        "rank": 4,
        "originalEng": "heavy"
      },
      {
        "word": "雨",
        "count": 34223,
        "cat": "geo",
        "trend": "up",
        "rank": 5,
        "originalEng": "rain"
      },
      {
        "word": "ランキング",
        "count": 31922,
        "cat": "econ",
        "trend": "down",
        "rank": 6,
        "originalEng": "rankings"
      },
      {
        "word": "中国",
        "count": 26397,
        "cat": "social",
        "trend": "down",
        "rank": 7,
        "originalEng": "china"
      },
      {
        "word": "3つ",
        "count": 23172,
        "cat": "tech",
        "trend": "up",
        "rank": 8,
        "originalEng": "three"
      },
      {
        "word": "予想される",
        "count": 18990,
        "cat": "geo",
        "trend": "up",
        "rank": 9,
        "originalEng": "expected"
      },
      {
        "word": "メディア",
        "count": 14788,
        "cat": "geo",
        "trend": "up",
        "rank": 10,
        "originalEng": "media"
      }
    ]
  }
}