{
  "US": {
    "name": "アメリカ",
    "flag": "🇺🇸",
    "score": 92,
    "trends": [
      {
        "word": "リンゴ",
        "count": 50579,
        "cat": "tech",
        "trend": "up",
        "rank": 1,
        "originalEng": "apple"
      },
      {
        "word": "イラン",
        "count": 47814,
        "cat": "tech",
        "trend": "up",
        "rank": 2,
        "originalEng": "iran"
      },
      {
        "word": "殺す",
        "count": 42833,
        "cat": "econ",
        "trend": "down",
        "rank": 3,
        "originalEng": "kills"
      },
      {
        "word": "充電済み",
        "count": 39230,
        "cat": "geo",
        "trend": "up",
        "rank": 4,
        "originalEng": "charged"
      },
      {
        "word": "among",
        "count": 34969,
        "cat": "geo",
        "trend": "up",
        "rank": 5,
        "originalEng": "among"
      },
      {
        "word": "の間でテスラ",
        "count": 30555,
        "cat": "social",
        "trend": "down",
        "rank": 6,
        "originalEng": "tesla"
      },
      {
        "word": "エロン",
        "count": 27489,
        "cat": "tech",
        "trend": "up",
        "rank": 7,
        "originalEng": "elon"
      },
      {
        "word": "ムスク",
        "count": 23584,
        "cat": "geo",
        "trend": "up",
        "rank": 8,
        "originalEng": "musk"
      },
      {
        "word": "戻る",
        "count": 18980,
        "cat": "social",
        "trend": "down",
        "rank": 9,
        "originalEng": "back"
      },
      {
        "word": "ナサ",
        "count": 15377,
        "cat": "econ",
        "trend": "down",
        "rank": 10,
        "originalEng": "nasa"
      }
    ]
  },
  "JP": {
    "name": "日本",
    "flag": "🇯🇵",
    "score": 78,
    "trends": [
      {
        "word": "夏",
        "count": 51937,
        "cat": "econ",
        "trend": "down",
        "rank": 1,
        "originalEng": "summer"
      },
      {
        "word": "イラン",
        "count": 46567,
        "cat": "tech",
        "trend": "up",
        "rank": 2,
        "originalEng": "iran"
      },
      {
        "word": "連続",
        "count": 43836,
        "cat": "tech",
        "trend": "up",
        "rank": 3,
        "originalEng": "consecutive"
      },
      {
        "word": "火災",
        "count": 39239,
        "cat": "econ",
        "trend": "down",
        "rank": 4,
        "originalEng": "fires"
      },
      {
        "word": "without",
        "count": 34625,
        "cat": "geo",
        "trend": "up",
        "rank": 5,
        "originalEng": "without"
      },
      {
        "word": "なし車",
        "count": 31465,
        "cat": "geo",
        "trend": "up",
        "rank": 6,
        "originalEng": "car"
      },
      {
        "word": "少ない",
        "count": 27299,
        "cat": "geo",
        "trend": "up",
        "rank": 7,
        "originalEng": "few"
      },
      {
        "word": "天気",
        "count": 22752,
        "cat": "geo",
        "trend": "up",
        "rank": 8,
        "originalEng": "weather"
      },
      {
        "word": "それ",
        "count": 18932,
        "cat": "geo",
        "trend": "up",
        "rank": 9,
        "originalEng": "its"
      },
      {
        "word": "チーフ",
        "count": 15504,
        "cat": "econ",
        "trend": "down",
        "rank": 10,
        "originalEng": "chief"
      }
    ]
  },
  "GB": {
    "name": "イギリス",
    "flag": "🇬🇧",
    "score": 61,
    "trends": [
      {
        "word": "イラン",
        "count": 51286,
        "cat": "tech",
        "trend": "up",
        "rank": 1,
        "originalEng": "iran"
      },
      {
        "word": "明らかにします",
        "count": 46830,
        "cat": "tech",
        "trend": "up",
        "rank": 2,
        "originalEng": "reveals"
      },
      {
        "word": "傷",
        "count": 42478,
        "cat": "geo",
        "trend": "up",
        "rank": 3,
        "originalEng": "scratches"
      },
      {
        "word": "ストライク",
        "count": 38083,
        "cat": "tech",
        "trend": "up",
        "rank": 4,
        "originalEng": "strike"
      },
      {
        "word": "ロンドン",
        "count": 35049,
        "cat": "geo",
        "trend": "up",
        "rank": 5,
        "originalEng": "london"
      },
      {
        "word": "始まります",
        "count": 30889,
        "cat": "tech",
        "trend": "up",
        "rank": 6,
        "originalEng": "begins"
      },
      {
        "word": "歌手",
        "count": 27291,
        "cat": "geo",
        "trend": "up",
        "rank": 7,
        "originalEng": "singer"
      },
      {
        "word": "殺人",
        "count": 22492,
        "cat": "econ",
        "trend": "down",
        "rank": 8,
        "originalEng": "murder"
      },
      {
        "word": "停戦",
        "count": 19669,
        "cat": "social",
        "trend": "down",
        "rank": 9,
        "originalEng": "ceasefire"
      },
      {
        "word": "ターゲット",
        "count": 15789,
        "cat": "social",
        "trend": "down",
        "rank": 10,
        "originalEng": "target"
      }
    ]
  },
  "DE": {
    "name": "ドイツ",
    "flag": "🇩🇪",
    "score": 67,
    "trends": [
      {
        "word": "カップ",
        "count": 51796,
        "cat": "tech",
        "trend": "up",
        "rank": 1,
        "originalEng": "cup"
      },
      {
        "word": "イラン",
        "count": 47951,
        "cat": "tech",
        "trend": "up",
        "rank": 2,
        "originalEng": "iran"
      },
      {
        "word": "また",
        "count": 43483,
        "cat": "geo",
        "trend": "up",
        "rank": 3,
        "originalEng": "again"
      },
      {
        "word": "ダメ",
        "count": 38070,
        "cat": "econ",
        "trend": "down",
        "rank": 4,
        "originalEng": "dont"
      },
      {
        "word": "知っています",
        "count": 35981,
        "cat": "social",
        "trend": "down",
        "rank": 5,
        "originalEng": "know"
      },
      {
        "word": "トランプ",
        "count": 30180,
        "cat": "tech",
        "trend": "up",
        "rank": 6,
        "originalEng": "trump"
      },
      {
        "word": "明らかにします",
        "count": 27539,
        "cat": "tech",
        "trend": "up",
        "rank": 7,
        "originalEng": "reveals"
      },
      {
        "word": "ユーロ",
        "count": 23886,
        "cat": "tech",
        "trend": "up",
        "rank": 8,
        "originalEng": "euros"
      },
      {
        "word": "欲しい",
        "count": 19342,
        "cat": "social",
        "trend": "down",
        "rank": 9,
        "originalEng": "wants"
      },
      {
        "word": "サッカー",
        "count": 14775,
        "cat": "econ",
        "trend": "down",
        "rank": 10,
        "originalEng": "football"
      }
    ]
  },
  "IN": {
    "name": "インド",
    "flag": "🇮🇳",
    "score": 82,
    "trends": [
      {
        "word": "イラン",
        "count": 50297,
        "cat": "tech",
        "trend": "up",
        "rank": 1,
        "originalEng": "iran"
      },
      {
        "word": "ホルムズ",
        "count": 47934,
        "cat": "econ",
        "trend": "down",
        "rank": 2,
        "originalEng": "hormuz"
      },
      {
        "word": "戦争",
        "count": 42234,
        "cat": "geo",
        "trend": "up",
        "rank": 3,
        "originalEng": "war"
      },
      {
        "word": "知っています",
        "count": 39025,
        "cat": "social",
        "trend": "down",
        "rank": 4,
        "originalEng": "know"
      },
      {
        "word": "ナサ",
        "count": 35922,
        "cat": "econ",
        "trend": "down",
        "rank": 5,
        "originalEng": "nasa"
      },
      {
        "word": "ベンガル",
        "count": 31409,
        "cat": "econ",
        "trend": "down",
        "rank": 6,
        "originalEng": "bengal"
      },
      {
        "word": "投票",
        "count": 27455,
        "cat": "econ",
        "trend": "down",
        "rank": 7,
        "originalEng": "voting"
      },
      {
        "word": "更新情報",
        "count": 22739,
        "cat": "tech",
        "trend": "up",
        "rank": 8,
        "originalEng": "updates"
      },
      {
        "word": "わかります",
        "count": 19076,
        "cat": "geo",
        "trend": "up",
        "rank": 9,
        "originalEng": "sees"
      },
      {
        "word": "インド",
        "count": 15668,
        "cat": "social",
        "trend": "down",
        "rank": 10,
        "originalEng": "india"
      }
    ]
  },
  "FR": {
    "name": "フランス",
    "flag": "🇫🇷",
    "score": 59,
    "trends": [
      {
        "word": "それ",
        "count": 50829,
        "cat": "geo",
        "trend": "up",
        "rank": 1,
        "originalEng": "its"
      },
      {
        "word": "戦争",
        "count": 46226,
        "cat": "geo",
        "trend": "up",
        "rank": 2,
        "originalEng": "war"
      },
      {
        "word": "トランプ",
        "count": 43119,
        "cat": "tech",
        "trend": "up",
        "rank": 3,
        "originalEng": "trump"
      },
      {
        "word": "ついに",
        "count": 38101,
        "cat": "econ",
        "trend": "down",
        "rank": 4,
        "originalEng": "finally"
      },
      {
        "word": "レバノン",
        "count": 34986,
        "cat": "econ",
        "trend": "down",
        "rank": 5,
        "originalEng": "lebanon"
      },
      {
        "word": "にもかかわらず",
        "count": 31373,
        "cat": "geo",
        "trend": "up",
        "rank": 6,
        "originalEng": "despite"
      },
      {
        "word": "管理",
        "count": 27117,
        "cat": "tech",
        "trend": "up",
        "rank": 7,
        "originalEng": "administration"
      },
      {
        "word": "なぜ",
        "count": 22630,
        "cat": "geo",
        "trend": "up",
        "rank": 8,
        "originalEng": "why"
      },
      {
        "word": "ドナルド",
        "count": 19844,
        "cat": "tech",
        "trend": "up",
        "rank": 9,
        "originalEng": "donald"
      },
      {
        "word": "人間",
        "count": 15865,
        "cat": "econ",
        "trend": "down",
        "rank": 10,
        "originalEng": "human"
      }
    ]
  },
  "AU": {
    "name": "オーストラリア",
    "flag": "🇦🇺",
    "score": 55,
    "trends": [
      {
        "word": "戦争",
        "count": 50343,
        "cat": "geo",
        "trend": "up",
        "rank": 1,
        "originalEng": "war"
      },
      {
        "word": "オーストラリア",
        "count": 47239,
        "cat": "geo",
        "trend": "up",
        "rank": 2,
        "originalEng": "australia"
      },
      {
        "word": "トランプ",
        "count": 43813,
        "cat": "tech",
        "trend": "up",
        "rank": 3,
        "originalEng": "trump"
      },
      {
        "word": "停戦",
        "count": 39726,
        "cat": "social",
        "trend": "down",
        "rank": 4,
        "originalEng": "ceasefire"
      },
      {
        "word": "殺す",
        "count": 35110,
        "cat": "tech",
        "trend": "up",
        "rank": 5,
        "originalEng": "kill"
      },
      {
        "word": "involving",
        "count": 30016,
        "cat": "tech",
        "trend": "up",
        "rank": 6,
        "originalEng": "involving"
      },
      {
        "word": "が関与する人生",
        "count": 27793,
        "cat": "geo",
        "trend": "up",
        "rank": 7,
        "originalEng": "life"
      },
      {
        "word": "シドニー",
        "count": 22214,
        "cat": "geo",
        "trend": "up",
        "rank": 8,
        "originalEng": "sydney"
      },
      {
        "word": "ホーム",
        "count": 18400,
        "cat": "social",
        "trend": "down",
        "rank": 9,
        "originalEng": "home"
      },
      {
        "word": "秘書",
        "count": 15438,
        "cat": "geo",
        "trend": "up",
        "rank": 10,
        "originalEng": "secretary"
      }
    ]
  },
  "KR": {
    "name": "韓国",
    "flag": "🇰🇷",
    "score": 74,
    "trends": [
      {
        "word": "それ",
        "count": 50805,
        "cat": "geo",
        "trend": "up",
        "rank": 1,
        "originalEng": "its"
      },
      {
        "word": "3つ",
        "count": 47585,
        "cat": "tech",
        "trend": "up",
        "rank": 2,
        "originalEng": "three"
      },
      {
        "word": "億",
        "count": 43867,
        "cat": "social",
        "trend": "down",
        "rank": 3,
        "originalEng": "billion"
      },
      {
        "word": "イラン",
        "count": 38961,
        "cat": "tech",
        "trend": "up",
        "rank": 4,
        "originalEng": "iran"
      },
      {
        "word": "油",
        "count": 35374,
        "cat": "tech",
        "trend": "up",
        "rank": 5,
        "originalEng": "oil"
      },
      {
        "word": "ジャン",
        "count": 31856,
        "cat": "geo",
        "trend": "up",
        "rank": 6,
        "originalEng": "jang"
      },
      {
        "word": "not",
        "count": 27658,
        "cat": "social",
        "trend": "down",
        "rank": 7,
        "originalEng": "not"
      },
      {
        "word": "ではありません",
        "count": 22541,
        "cat": "geo",
        "trend": "up",
        "rank": 8,
        "originalEng": "change"
      },
      {
        "word": "変更",
        "count": 18373,
        "cat": "social",
        "trend": "down",
        "rank": 9,
        "originalEng": "breaking"
      },
      {
        "word": "壊れる",
        "count": 14587,
        "cat": "econ",
        "trend": "down",
        "rank": 10,
        "originalEng": "sentenced"
      }
    ]
  },
  "BR": {
    "name": "ブラジル",
    "flag": "🇧🇷",
    "score": 52,
    "trends": [
      {
        "word": "判決を受けた",
        "count": 51118,
        "cat": "social",
        "trend": "down",
        "rank": 1,
        "originalEng": "against"
      },
      {
        "word": "反対",
        "count": 46814,
        "cat": "tech",
        "trend": "up",
        "rank": 2,
        "originalEng": "bbb"
      },
      {
        "word": "BB",
        "count": 42836,
        "cat": "econ",
        "trend": "down",
        "rank": 3,
        "originalEng": "agent"
      },
      {
        "word": "エージェント",
        "count": 38544,
        "cat": "geo",
        "trend": "up",
        "rank": 4,
        "originalEng": "credentials"
      },
      {
        "word": "資格情報",
        "count": 35548,
        "cat": "tech",
        "trend": "up",
        "rank": 5,
        "originalEng": "approves"
      },
      {
        "word": "承認します",
        "count": 31624,
        "cat": "social",
        "trend": "down",
        "rank": 6,
        "originalEng": "end"
      },
      {
        "word": "終わり",
        "count": 27512,
        "cat": "geo",
        "trend": "up",
        "rank": 7,
        "originalEng": "arrested"
      },
      {
        "word": "逮捕されました",
        "count": 22172,
        "cat": "geo",
        "trend": "up",
        "rank": 8,
        "originalEng": "rio"
      },
      {
        "word": "リオ",
        "count": 19199,
        "cat": "geo",
        "trend": "up",
        "rank": 9,
        "originalEng": "dead"
      },
      {
        "word": "死んだ",
        "count": 14402,
        "cat": "econ",
        "trend": "down",
        "rank": 10,
        "originalEng": "calls"
      }
    ]
  },
  "CA": {
    "name": "カナダ",
    "flag": "🇨🇦",
    "score": 58,
    "trends": [
      {
        "word": "jet",
        "count": 50234,
        "cat": "econ",
        "trend": "down",
        "rank": 1,
        "originalEng": "jet"
      },
      {
        "word": "を呼び出しますジェット",
        "count": 47979,
        "cat": "geo",
        "trend": "up",
        "rank": 2,
        "originalEng": "death"
      },
      {
        "word": "死",
        "count": 42074,
        "cat": "social",
        "trend": "down",
        "rank": 3,
        "originalEng": "alberta"
      },
      {
        "word": "アルバータ州",
        "count": 39844,
        "cat": "geo",
        "trend": "up",
        "rank": 4,
        "originalEng": "ontario"
      },
      {
        "word": "オンタリオ州",
        "count": 34590,
        "cat": "geo",
        "trend": "up",
        "rank": 5,
        "originalEng": "premier"
      },
      {
        "word": "プレミア",
        "count": 30913,
        "cat": "econ",
        "trend": "down",
        "rank": 6,
        "originalEng": "shooting"
      },
      {
        "word": "射撃",
        "count": 27141,
        "cat": "social",
        "trend": "down",
        "rank": 7,
        "originalEng": "calgary"
      },
      {
        "word": "戦争",
        "count": 23394,
        "cat": "geo",
        "trend": "up",
        "rank": 8,
        "originalEng": "war"
      },
      {
        "word": "カルガリー",
        "count": 18776,
        "cat": "social",
        "trend": "down",
        "rank": 9,
        "originalEng": "prediction"
      },
      {
        "word": "予測",
        "count": 15018,
        "cat": "tech",
        "trend": "up",
        "rank": 10,
        "originalEng": "canada"
      }
    ]
  },
  "RU": {
    "name": "ロシア",
    "flag": "🇷🇺",
    "score": 80,
    "trends": [
      {
        "word": "カナダ",
        "count": 51479,
        "cat": "social",
        "trend": "down",
        "rank": 1,
        "originalEng": "fell"
      },
      {
        "word": "not",
        "count": 47561,
        "cat": "social",
        "trend": "down",
        "rank": 2,
        "originalEng": "not"
      },
      {
        "word": "落ちた",
        "count": 42489,
        "cat": "social",
        "trend": "down",
        "rank": 3,
        "originalEng": "whom"
      },
      {
        "word": "誰",
        "count": 38922,
        "cat": "tech",
        "trend": "up",
        "rank": 4,
        "originalEng": "friendship"
      },
      {
        "word": "億",
        "count": 34341,
        "cat": "social",
        "trend": "down",
        "rank": 5,
        "originalEng": "billion"
      },
      {
        "word": "友情",
        "count": 30805,
        "cat": "tech",
        "trend": "up",
        "rank": 6,
        "originalEng": "fire"
      },
      {
        "word": "火",
        "count": 26777,
        "cat": "geo",
        "trend": "up",
        "rank": 7,
        "originalEng": "loan"
      },
      {
        "word": "ローン",
        "count": 22703,
        "cat": "social",
        "trend": "down",
        "rank": 8,
        "originalEng": "kyiv"
      },
      {
        "word": "モスクワ",
        "count": 19752,
        "cat": "tech",
        "trend": "up",
        "rank": 9,
        "originalEng": "moscow"
      },
      {
        "word": "became",
        "count": 15665,
        "cat": "social",
        "trend": "down",
        "rank": 10,
        "originalEng": "became"
      }
    ]
  },
  "CN": {
    "name": "中国",
    "flag": "🇨🇳",
    "score": 85,
    "trends": [
      {
        "word": "になりました在庫",
        "count": 50522,
        "cat": "tech",
        "trend": "up",
        "rank": 1,
        "originalEng": "stock"
      },
      {
        "word": "価格",
        "count": 46169,
        "cat": "econ",
        "trend": "down",
        "rank": 2,
        "originalEng": "price"
      },
      {
        "word": "ホン",
        "count": 42487,
        "cat": "geo",
        "trend": "up",
        "rank": 3,
        "originalEng": "hong"
      },
      {
        "word": "コン",
        "count": 38101,
        "cat": "econ",
        "trend": "down",
        "rank": 4,
        "originalEng": "kong"
      },
      {
        "word": "友情",
        "count": 35666,
        "cat": "tech",
        "trend": "up",
        "rank": 5,
        "originalEng": "fire"
      },
      {
        "word": "停戦",
        "count": 30072,
        "cat": "social",
        "trend": "down",
        "rank": 6,
        "originalEng": "ceasefire"
      },
      {
        "word": "部門",
        "count": 26401,
        "cat": "tech",
        "trend": "up",
        "rank": 7,
        "originalEng": "department"
      },
      {
        "word": "上げた",
        "count": 23850,
        "cat": "geo",
        "trend": "up",
        "rank": 8,
        "originalEng": "raised"
      },
      {
        "word": "トランプ",
        "count": 18440,
        "cat": "tech",
        "trend": "up",
        "rank": 9,
        "originalEng": "trump"
      },
      {
        "word": "封鎖",
        "count": 15994,
        "cat": "social",
        "trend": "down",
        "rank": 10,
        "originalEng": "blockade"
      }
    ]
  }
}