{
  "US": {
    "name": "アメリカ",
    "flag": "🇺🇸",
    "score": 92,
    "trends": [
      {
        "word": "イラン",
        "count": 51367,
        "cat": "tech",
        "trend": "up",
        "rank": 1,
        "originalEng": "iran"
      },
      {
        "word": "カップ",
        "count": 46162,
        "cat": "tech",
        "trend": "up",
        "rank": 2,
        "originalEng": "cup"
      },
      {
        "word": "更新情報",
        "count": 42010,
        "cat": "tech",
        "trend": "up",
        "rank": 3,
        "originalEng": "updates"
      },
      {
        "word": "トランプ",
        "count": 39987,
        "cat": "tech",
        "trend": "up",
        "rank": 4,
        "originalEng": "trump"
      },
      {
        "word": "それ",
        "count": 34716,
        "cat": "geo",
        "trend": "up",
        "rank": 5,
        "originalEng": "its"
      },
      {
        "word": "難しい",
        "count": 30490,
        "cat": "social",
        "trend": "down",
        "rank": 6,
        "originalEng": "hard"
      },
      {
        "word": "キー",
        "count": 27657,
        "cat": "social",
        "trend": "down",
        "rank": 7,
        "originalEng": "key"
      },
      {
        "word": "テイクアウト",
        "count": 23589,
        "cat": "tech",
        "trend": "up",
        "rank": 8,
        "originalEng": "takeaways"
      },
      {
        "word": "メイン",
        "count": 19375,
        "cat": "geo",
        "trend": "up",
        "rank": 9,
        "originalEng": "maine"
      },
      {
        "word": "南",
        "count": 15524,
        "cat": "econ",
        "trend": "down",
        "rank": 10,
        "originalEng": "south"
      }
    ]
  },
  "JP": {
    "name": "日本",
    "flag": "🇯🇵",
    "score": 78,
    "trends": [
      {
        "word": "イラン",
        "count": 50876,
        "cat": "tech",
        "trend": "up",
        "rank": 1,
        "originalEng": "iran"
      },
      {
        "word": "軍事",
        "count": 46878,
        "cat": "social",
        "trend": "down",
        "rank": 2,
        "originalEng": "military"
      },
      {
        "word": "日本語",
        "count": 42554,
        "cat": "social",
        "trend": "down",
        "rank": 3,
        "originalEng": "japanese"
      },
      {
        "word": "トランプ",
        "count": 38747,
        "cat": "tech",
        "trend": "up",
        "rank": 4,
        "originalEng": "trump"
      },
      {
        "word": "帝国",
        "count": 34234,
        "cat": "econ",
        "trend": "down",
        "rank": 5,
        "originalEng": "imperial"
      },
      {
        "word": "番号",
        "count": 30247,
        "cat": "social",
        "trend": "down",
        "rank": 6,
        "originalEng": "number"
      },
      {
        "word": "家族",
        "count": 26869,
        "cat": "geo",
        "trend": "up",
        "rank": 7,
        "originalEng": "family"
      },
      {
        "word": "建設",
        "count": 23581,
        "cat": "social",
        "trend": "down",
        "rank": 8,
        "originalEng": "construction"
      },
      {
        "word": "壊れる",
        "count": 18584,
        "cat": "social",
        "trend": "down",
        "rank": 9,
        "originalEng": "breaking"
      },
      {
        "word": "中国語",
        "count": 15626,
        "cat": "econ",
        "trend": "down",
        "rank": 10,
        "originalEng": "chinese"
      }
    ]
  },
  "GB": {
    "name": "イギリス",
    "flag": "🇬🇧",
    "score": 61,
    "trends": [
      {
        "word": "攻撃",
        "count": 51678,
        "cat": "geo",
        "trend": "up",
        "rank": 1,
        "originalEng": "attack"
      },
      {
        "word": "ベルファスト",
        "count": 47129,
        "cat": "social",
        "trend": "down",
        "rank": 2,
        "originalEng": "belfast"
      },
      {
        "word": "イラン",
        "count": 42671,
        "cat": "tech",
        "trend": "up",
        "rank": 3,
        "originalEng": "iran"
      },
      {
        "word": "終わり",
        "count": 39006,
        "cat": "social",
        "trend": "down",
        "rank": 4,
        "originalEng": "end"
      },
      {
        "word": "暴力",
        "count": 35192,
        "cat": "social",
        "trend": "down",
        "rank": 5,
        "originalEng": "violence"
      },
      {
        "word": "トランプ",
        "count": 30338,
        "cat": "tech",
        "trend": "up",
        "rank": 6,
        "originalEng": "trump"
      },
      {
        "word": "ヒット",
        "count": 27754,
        "cat": "social",
        "trend": "down",
        "rank": 7,
        "originalEng": "hit"
      },
      {
        "word": "殺人",
        "count": 22046,
        "cat": "econ",
        "trend": "down",
        "rank": 8,
        "originalEng": "murder"
      },
      {
        "word": "投獄されました",
        "count": 18528,
        "cat": "social",
        "trend": "down",
        "rank": 9,
        "originalEng": "jailed"
      },
      {
        "word": "左",
        "count": 15446,
        "cat": "social",
        "trend": "down",
        "rank": 10,
        "originalEng": "left"
      }
    ]
  },
  "DE": {
    "name": "ドイツ",
    "flag": "🇩🇪",
    "score": 67,
    "trends": [
      {
        "word": "メルツ",
        "count": 51076,
        "cat": "geo",
        "trend": "up",
        "rank": 1,
        "originalEng": "merz"
      },
      {
        "word": "not",
        "count": 47308,
        "cat": "social",
        "trend": "down",
        "rank": 2,
        "originalEng": "not"
      },
      {
        "word": "ではありません",
        "count": 43786,
        "cat": "geo",
        "trend": "up",
        "rank": 3,
        "originalEng": "cancer"
      },
      {
        "word": "カップ",
        "count": 38565,
        "cat": "tech",
        "trend": "up",
        "rank": 4,
        "originalEng": "cup"
      },
      {
        "word": "がん",
        "count": 34711,
        "cat": "geo",
        "trend": "up",
        "rank": 5,
        "originalEng": "musk"
      },
      {
        "word": "トランプ",
        "count": 30157,
        "cat": "tech",
        "trend": "up",
        "rank": 6,
        "originalEng": "trump"
      },
      {
        "word": "発表します",
        "count": 27169,
        "cat": "tech",
        "trend": "up",
        "rank": 7,
        "originalEng": "announces"
      },
      {
        "word": "スペース",
        "count": 22561,
        "cat": "tech",
        "trend": "up",
        "rank": 8,
        "originalEng": "space"
      },
      {
        "word": "割引",
        "count": 19611,
        "cat": "econ",
        "trend": "down",
        "rank": 9,
        "originalEng": "discount"
      },
      {
        "word": "する",
        "count": 15877,
        "cat": "econ",
        "trend": "down",
        "rank": 10,
        "originalEng": "does"
      }
    ]
  },
  "IN": {
    "name": "インド",
    "flag": "🇮🇳",
    "score": 82,
    "trends": [
      {
        "word": "イラン",
        "count": 50752,
        "cat": "tech",
        "trend": "up",
        "rank": 1,
        "originalEng": "iran"
      },
      {
        "word": "危機",
        "count": 47818,
        "cat": "econ",
        "trend": "down",
        "rank": 2,
        "originalEng": "crisis"
      },
      {
        "word": "インド",
        "count": 43403,
        "cat": "social",
        "trend": "down",
        "rank": 3,
        "originalEng": "india"
      },
      {
        "word": "モディ",
        "count": 39283,
        "cat": "social",
        "trend": "down",
        "rank": 4,
        "originalEng": "modi"
      },
      {
        "word": "乗組員",
        "count": 35933,
        "cat": "econ",
        "trend": "down",
        "rank": 5,
        "originalEng": "crew"
      },
      {
        "word": "撮影されました",
        "count": 30032,
        "cat": "social",
        "trend": "down",
        "rank": 6,
        "originalEng": "taken"
      },
      {
        "word": "トランプ",
        "count": 27391,
        "cat": "tech",
        "trend": "up",
        "rank": 7,
        "originalEng": "trump"
      },
      {
        "word": "amid",
        "count": 22973,
        "cat": "social",
        "trend": "down",
        "rank": 8,
        "originalEng": "amid"
      },
      {
        "word": "の中でママタ",
        "count": 19025,
        "cat": "social",
        "trend": "down",
        "rank": 9,
        "originalEng": "mamata"
      },
      {
        "word": "meets",
        "count": 15577,
        "cat": "geo",
        "trend": "up",
        "rank": 10,
        "originalEng": "meets"
      }
    ]
  },
  "FR": {
    "name": "フランス",
    "flag": "🇫🇷",
    "score": 59,
    "trends": [
      {
        "word": "を満たす",
        "count": 51976,
        "cat": "econ",
        "trend": "down",
        "rank": 1,
        "originalEng": "united"
      },
      {
        "word": "団結",
        "count": 46455,
        "cat": "tech",
        "trend": "up",
        "rank": 2,
        "originalEng": "states"
      },
      {
        "word": "状態",
        "count": 43126,
        "cat": "social",
        "trend": "down",
        "rank": 3,
        "originalEng": "affair"
      },
      {
        "word": "不倫",
        "count": 38719,
        "cat": "geo",
        "trend": "up",
        "rank": 4,
        "originalEng": "already"
      },
      {
        "word": "すでに",
        "count": 35101,
        "cat": "geo",
        "trend": "up",
        "rank": 5,
        "originalEng": "war"
      },
      {
        "word": "ヒット",
        "count": 31772,
        "cat": "social",
        "trend": "down",
        "rank": 6,
        "originalEng": "hit"
      },
      {
        "word": "戦争",
        "count": 26653,
        "cat": "social",
        "trend": "down",
        "rank": 7,
        "originalEng": "lyhanna"
      },
      {
        "word": "not",
        "count": 22644,
        "cat": "social",
        "trend": "down",
        "rank": 8,
        "originalEng": "not"
      },
      {
        "word": "リハンナ",
        "count": 19162,
        "cat": "geo",
        "trend": "up",
        "rank": 9,
        "originalEng": "case"
      },
      {
        "word": "場合",
        "count": 14602,
        "cat": "tech",
        "trend": "up",
        "rank": 10,
        "originalEng": "french"
      }
    ]
  },
  "AU": {
    "name": "オーストラリア",
    "flag": "🇦🇺",
    "score": 55,
    "trends": [
      {
        "word": "攻撃",
        "count": 50658,
        "cat": "geo",
        "trend": "up",
        "rank": 1,
        "originalEng": "attack"
      },
      {
        "word": "イラン",
        "count": 47349,
        "cat": "tech",
        "trend": "up",
        "rank": 2,
        "originalEng": "iran"
      },
      {
        "word": "フランス語",
        "count": 42790,
        "cat": "geo",
        "trend": "up",
        "rank": 3,
        "originalEng": "met"
      },
      {
        "word": "会った",
        "count": 39273,
        "cat": "social",
        "trend": "down",
        "rank": 4,
        "originalEng": "court"
      },
      {
        "word": "法廷",
        "count": 34149,
        "cat": "econ",
        "trend": "down",
        "rank": 5,
        "originalEng": "nation"
      },
      {
        "word": "国家",
        "count": 31457,
        "cat": "social",
        "trend": "down",
        "rank": 6,
        "originalEng": "budget"
      },
      {
        "word": "左",
        "count": 26857,
        "cat": "social",
        "trend": "down",
        "rank": 7,
        "originalEng": "left"
      },
      {
        "word": "すでに",
        "count": 23883,
        "cat": "geo",
        "trend": "up",
        "rank": 8,
        "originalEng": "war"
      },
      {
        "word": "予算",
        "count": 19761,
        "cat": "social",
        "trend": "down",
        "rank": 9,
        "originalEng": "home"
      },
      {
        "word": "ホーム",
        "count": 15530,
        "cat": "geo",
        "trend": "up",
        "rank": 10,
        "originalEng": "second"
      }
    ]
  },
  "KR": {
    "name": "韓国",
    "flag": "🇰🇷",
    "score": 74,
    "trends": [
      {
        "word": "2 番目",
        "count": 51274,
        "cat": "tech",
        "trend": "up",
        "rank": 1,
        "originalEng": "national"
      },
      {
        "word": "全国",
        "count": 47831,
        "cat": "social",
        "trend": "down",
        "rank": 2,
        "originalEng": "election"
      },
      {
        "word": "イラン",
        "count": 42401,
        "cat": "tech",
        "trend": "up",
        "rank": 3,
        "originalEng": "iran"
      },
      {
        "word": "選挙",
        "count": 38715,
        "cat": "geo",
        "trend": "up",
        "rank": 4,
        "originalEng": "lee"
      },
      {
        "word": "リー",
        "count": 35001,
        "cat": "econ",
        "trend": "down",
        "rank": 5,
        "originalEng": "nintendo"
      },
      {
        "word": "パーティー",
        "count": 31319,
        "cat": "tech",
        "trend": "up",
        "rank": 6,
        "originalEng": "party"
      },
      {
        "word": "トランプ",
        "count": 27859,
        "cat": "tech",
        "trend": "up",
        "rank": 7,
        "originalEng": "trump"
      },
      {
        "word": "not",
        "count": 23615,
        "cat": "social",
        "trend": "down",
        "rank": 8,
        "originalEng": "not"
      },
      {
        "word": "社長",
        "count": 18550,
        "cat": "geo",
        "trend": "up",
        "rank": 9,
        "originalEng": "president"
      },
      {
        "word": "lets",
        "count": 14878,
        "cat": "geo",
        "trend": "up",
        "rank": 10,
        "originalEng": "lets"
      }
    ]
  },
  "BR": {
    "name": "ブラジル",
    "flag": "🇧🇷",
    "score": 52,
    "trends": [
      {
        "word": "しましょう承認します",
        "count": 50966,
        "cat": "tech",
        "trend": "up",
        "rank": 1,
        "originalEng": "approves"
      },
      {
        "word": "委員会",
        "count": 47325,
        "cat": "social",
        "trend": "down",
        "rank": 2,
        "originalEng": "committee"
      },
      {
        "word": "クエスト",
        "count": 43256,
        "cat": "social",
        "trend": "down",
        "rank": 3,
        "originalEng": "quaest"
      },
      {
        "word": "投票",
        "count": 38437,
        "cat": "tech",
        "trend": "up",
        "rank": 4,
        "originalEng": "vote"
      },
      {
        "word": "影響",
        "count": 35469,
        "cat": "tech",
        "trend": "up",
        "rank": 5,
        "originalEng": "impact"
      },
      {
        "word": "上院",
        "count": 31307,
        "cat": "tech",
        "trend": "up",
        "rank": 6,
        "originalEng": "senate"
      },
      {
        "word": "ペック",
        "count": 26547,
        "cat": "tech",
        "trend": "up",
        "rank": 7,
        "originalEng": "pec"
      },
      {
        "word": "億",
        "count": 22347,
        "cat": "social",
        "trend": "down",
        "rank": 8,
        "originalEng": "billion"
      },
      {
        "word": "ルラ",
        "count": 19903,
        "cat": "tech",
        "trend": "up",
        "rank": 9,
        "originalEng": "lula"
      },
      {
        "word": "トランプ",
        "count": 14487,
        "cat": "tech",
        "trend": "up",
        "rank": 10,
        "originalEng": "trump"
      }
    ]
  },
  "CA": {
    "name": "カナダ",
    "flag": "🇨🇦",
    "score": 58,
    "trends": [
      {
        "word": "カナダ",
        "count": 51464,
        "cat": "tech",
        "trend": "up",
        "rank": 1,
        "originalEng": "canada"
      },
      {
        "word": "カップ",
        "count": 46014,
        "cat": "tech",
        "trend": "up",
        "rank": 2,
        "originalEng": "cup"
      },
      {
        "word": "トランプ",
        "count": 43088,
        "cat": "tech",
        "trend": "up",
        "rank": 3,
        "originalEng": "trump"
      },
      {
        "word": "脅す",
        "count": 39951,
        "cat": "geo",
        "trend": "up",
        "rank": 4,
        "originalEng": "threatens"
      },
      {
        "word": "not",
        "count": 34517,
        "cat": "social",
        "trend": "down",
        "rank": 5,
        "originalEng": "not"
      },
      {
        "word": "取引",
        "count": 31688,
        "cat": "geo",
        "trend": "up",
        "rank": 6,
        "originalEng": "deal"
      },
      {
        "word": "オープニング",
        "count": 27864,
        "cat": "geo",
        "trend": "up",
        "rank": 7,
        "originalEng": "opening"
      },
      {
        "word": "殺されました",
        "count": 23715,
        "cat": "social",
        "trend": "down",
        "rank": 8,
        "originalEng": "killed"
      },
      {
        "word": "火",
        "count": 19310,
        "cat": "tech",
        "trend": "up",
        "rank": 9,
        "originalEng": "fire"
      },
      {
        "word": "カンファレンス",
        "count": 14315,
        "cat": "geo",
        "trend": "up",
        "rank": 10,
        "originalEng": "conference"
      }
    ]
  },
  "RU": {
    "name": "ロシア",
    "flag": "🇷🇺",
    "score": 80,
    "trends": [
      {
        "word": "インフレ",
        "count": 51432,
        "cat": "tech",
        "trend": "up",
        "rank": 1,
        "originalEng": "inflation"
      },
      {
        "word": "武装",
        "count": 47329,
        "cat": "social",
        "trend": "down",
        "rank": 2,
        "originalEng": "armed"
      },
      {
        "word": "力",
        "count": 42269,
        "cat": "geo",
        "trend": "up",
        "rank": 3,
        "originalEng": "forces"
      },
      {
        "word": "プーチン",
        "count": 39934,
        "cat": "geo",
        "trend": "up",
        "rank": 4,
        "originalEng": "putin"
      },
      {
        "word": "ロシア語",
        "count": 34267,
        "cat": "social",
        "trend": "down",
        "rank": 5,
        "originalEng": "russian"
      },
      {
        "word": "結果",
        "count": 31141,
        "cat": "tech",
        "trend": "up",
        "rank": 6,
        "originalEng": "results"
      },
      {
        "word": "期限",
        "count": 27285,
        "cat": "geo",
        "trend": "up",
        "rank": 7,
        "originalEng": "due"
      },
      {
        "word": "攻撃",
        "count": 23830,
        "cat": "geo",
        "trend": "up",
        "rank": 8,
        "originalEng": "attack"
      },
      {
        "word": "始まりました",
        "count": 19051,
        "cat": "econ",
        "trend": "down",
        "rank": 9,
        "originalEng": "began"
      },
      {
        "word": "ロシア",
        "count": 15563,
        "cat": "econ",
        "trend": "down",
        "rank": 10,
        "originalEng": "russia"
      }
    ]
  },
  "CN": {
    "name": "中国",
    "flag": "🇨🇳",
    "score": 85,
    "trends": [
      {
        "word": "人生",
        "count": 50433,
        "cat": "geo",
        "trend": "up",
        "rank": 1,
        "originalEng": "life"
      },
      {
        "word": "ホン",
        "count": 47045,
        "cat": "geo",
        "trend": "up",
        "rank": 2,
        "originalEng": "hong"
      },
      {
        "word": "許可されました",
        "count": 43288,
        "cat": "social",
        "trend": "down",
        "rank": 3,
        "originalEng": "granted"
      },
      {
        "word": "保釈金",
        "count": 38790,
        "cat": "tech",
        "trend": "up",
        "rank": 4,
        "originalEng": "bail"
      },
      {
        "word": "メッセージ",
        "count": 34023,
        "cat": "social",
        "trend": "down",
        "rank": 5,
        "originalEng": "message"
      },
      {
        "word": "キム",
        "count": 30109,
        "cat": "social",
        "trend": "down",
        "rank": 6,
        "originalEng": "kim"
      },
      {
        "word": "落ちた",
        "count": 26833,
        "cat": "social",
        "trend": "down",
        "rank": 7,
        "originalEng": "fell"
      },
      {
        "word": "株式",
        "count": 23023,
        "cat": "geo",
        "trend": "up",
        "rank": 8,
        "originalEng": "shares"
      },
      {
        "word": "影",
        "count": 18707,
        "cat": "geo",
        "trend": "up",
        "rank": 9,
        "originalEng": "shadow"
      },
      {
        "word": "コン",
        "count": 14048,
        "cat": "econ",
        "trend": "down",
        "rank": 10,
        "originalEng": "kong"
      }
    ]
  }
}