{
  "US": {
    "name": "アメリカ",
    "flag": "🇺🇸",
    "score": 92,
    "trends": [
      {
        "word": "トランプ",
        "count": 50247,
        "cat": "tech",
        "trend": "up",
        "rank": 1,
        "originalEng": "trump"
      },
      {
        "word": "calls",
        "count": 47512,
        "cat": "econ",
        "trend": "down",
        "rank": 2,
        "originalEng": "calls"
      },
      {
        "word": "を呼び出します提案",
        "count": 43734,
        "cat": "tech",
        "trend": "up",
        "rank": 3,
        "originalEng": "proposal"
      },
      {
        "word": "死んだ",
        "count": 39337,
        "cat": "geo",
        "trend": "up",
        "rank": 4,
        "originalEng": "dead"
      },
      {
        "word": "かもしれません",
        "count": 35273,
        "cat": "econ",
        "trend": "down",
        "rank": 5,
        "originalEng": "may"
      },
      {
        "word": "クルーズ",
        "count": 30748,
        "cat": "social",
        "trend": "down",
        "rank": 6,
        "originalEng": "cruise"
      },
      {
        "word": "船",
        "count": 26447,
        "cat": "geo",
        "trend": "up",
        "rank": 7,
        "originalEng": "ship"
      },
      {
        "word": "にもかかわらず",
        "count": 23458,
        "cat": "geo",
        "trend": "up",
        "rank": 8,
        "originalEng": "despite"
      },
      {
        "word": "ジャンプ",
        "count": 18890,
        "cat": "tech",
        "trend": "up",
        "rank": 9,
        "originalEng": "jump"
      },
      {
        "word": "ステップ",
        "count": 15980,
        "cat": "social",
        "trend": "down",
        "rank": 10,
        "originalEng": "steps"
      }
    ]
  },
  "JP": {
    "name": "日本",
    "flag": "🇯🇵",
    "score": 78,
    "trends": [
      {
        "word": "円",
        "count": 51518,
        "cat": "tech",
        "trend": "up",
        "rank": 1,
        "originalEng": "yen"
      },
      {
        "word": "かもしれません",
        "count": 47070,
        "cat": "econ",
        "trend": "down",
        "rank": 2,
        "originalEng": "may"
      },
      {
        "word": "勝利",
        "count": 43925,
        "cat": "tech",
        "trend": "up",
        "rank": 3,
        "originalEng": "victory"
      },
      {
        "word": "日本",
        "count": 38170,
        "cat": "tech",
        "trend": "up",
        "rank": 4,
        "originalEng": "japan"
      },
      {
        "word": "なぜ",
        "count": 35094,
        "cat": "geo",
        "trend": "up",
        "rank": 5,
        "originalEng": "why"
      },
      {
        "word": "兄弟",
        "count": 30366,
        "cat": "social",
        "trend": "down",
        "rank": 6,
        "originalEng": "brothers"
      },
      {
        "word": "トランプ",
        "count": 26948,
        "cat": "tech",
        "trend": "up",
        "rank": 7,
        "originalEng": "trump"
      },
      {
        "word": "問題",
        "count": 23270,
        "cat": "econ",
        "trend": "down",
        "rank": 8,
        "originalEng": "issue"
      },
      {
        "word": "政府",
        "count": 18907,
        "cat": "econ",
        "trend": "down",
        "rank": 9,
        "originalEng": "government"
      },
      {
        "word": "発表します",
        "count": 14260,
        "cat": "tech",
        "trend": "up",
        "rank": 10,
        "originalEng": "announces"
      }
    ]
  },
  "GB": {
    "name": "イギリス",
    "flag": "🇬🇧",
    "score": 61,
    "trends": [
      {
        "word": "スターマー",
        "count": 50018,
        "cat": "geo",
        "trend": "up",
        "rank": 1,
        "originalEng": "starmer"
      },
      {
        "word": "選挙",
        "count": 46151,
        "cat": "social",
        "trend": "down",
        "rank": 2,
        "originalEng": "election"
      },
      {
        "word": "終わり",
        "count": 42262,
        "cat": "social",
        "trend": "down",
        "rank": 3,
        "originalEng": "end"
      },
      {
        "word": "戦争",
        "count": 39031,
        "cat": "geo",
        "trend": "up",
        "rank": 4,
        "originalEng": "war"
      },
      {
        "word": "にもかかわらず",
        "count": 34992,
        "cat": "geo",
        "trend": "up",
        "rank": 5,
        "originalEng": "despite"
      },
      {
        "word": "トランプ",
        "count": 30557,
        "cat": "tech",
        "trend": "up",
        "rank": 6,
        "originalEng": "trump"
      },
      {
        "word": "イラン",
        "count": 26802,
        "cat": "tech",
        "trend": "up",
        "rank": 7,
        "originalEng": "iran"
      },
      {
        "word": "いっぱい",
        "count": 22354,
        "cat": "social",
        "trend": "down",
        "rank": 8,
        "originalEng": "full"
      },
      {
        "word": "ステートメント",
        "count": 18823,
        "cat": "econ",
        "trend": "down",
        "rank": 9,
        "originalEng": "statement"
      },
      {
        "word": "結果",
        "count": 14269,
        "cat": "tech",
        "trend": "up",
        "rank": 10,
        "originalEng": "results"
      }
    ]
  },
  "DE": {
    "name": "ドイツ",
    "flag": "🇩🇪",
    "score": 67,
    "trends": [
      {
        "word": "戦争",
        "count": 50032,
        "cat": "geo",
        "trend": "up",
        "rank": 1,
        "originalEng": "war"
      },
      {
        "word": "トランプ",
        "count": 46373,
        "cat": "tech",
        "trend": "up",
        "rank": 2,
        "originalEng": "trump"
      },
      {
        "word": "反対",
        "count": 43637,
        "cat": "social",
        "trend": "down",
        "rank": 3,
        "originalEng": "against"
      },
      {
        "word": "shows",
        "count": 38318,
        "cat": "tech",
        "trend": "up",
        "rank": 4,
        "originalEng": "shows"
      },
      {
        "word": "イラン",
        "count": 34700,
        "cat": "tech",
        "trend": "up",
        "rank": 5,
        "originalEng": "iran"
      },
      {
        "word": "を示します勝ちます",
        "count": 30011,
        "cat": "social",
        "trend": "down",
        "rank": 6,
        "originalEng": "wins"
      },
      {
        "word": "止まる",
        "count": 27931,
        "cat": "econ",
        "trend": "down",
        "rank": 7,
        "originalEng": "stops"
      },
      {
        "word": "ストライク",
        "count": 22951,
        "cat": "tech",
        "trend": "up",
        "rank": 8,
        "originalEng": "strike"
      },
      {
        "word": "本物",
        "count": 19531,
        "cat": "tech",
        "trend": "up",
        "rank": 9,
        "originalEng": "real"
      },
      {
        "word": "接続",
        "count": 15980,
        "cat": "tech",
        "trend": "up",
        "rank": 10,
        "originalEng": "connection"
      }
    ]
  },
  "IN": {
    "name": "インド",
    "flag": "🇮🇳",
    "score": 82,
    "trends": [
      {
        "word": "かもしれません",
        "count": 51526,
        "cat": "econ",
        "trend": "down",
        "rank": 1,
        "originalEng": "may"
      },
      {
        "word": "イラン",
        "count": 46543,
        "cat": "tech",
        "trend": "up",
        "rank": 2,
        "originalEng": "iran"
      },
      {
        "word": "ビジェイ",
        "count": 43473,
        "cat": "geo",
        "trend": "up",
        "rank": 3,
        "originalEng": "vijays"
      },
      {
        "word": "トランプ",
        "count": 38667,
        "cat": "tech",
        "trend": "up",
        "rank": 4,
        "originalEng": "trump"
      },
      {
        "word": "インド",
        "count": 34726,
        "cat": "social",
        "trend": "down",
        "rank": 5,
        "originalEng": "india"
      },
      {
        "word": "オイル",
        "count": 30758,
        "cat": "tech",
        "trend": "up",
        "rank": 6,
        "originalEng": "oil"
      },
      {
        "word": "ムラ",
        "count": 27499,
        "cat": "tech",
        "trend": "up",
        "rank": 7,
        "originalEng": "mla"
      },
      {
        "word": "タミル語",
        "count": 22582,
        "cat": "social",
        "trend": "down",
        "rank": 8,
        "originalEng": "tamil"
      },
      {
        "word": "停戦",
        "count": 18558,
        "cat": "social",
        "trend": "down",
        "rank": 9,
        "originalEng": "ceasefire"
      },
      {
        "word": "を呼び出します提案",
        "count": 14989,
        "cat": "tech",
        "trend": "up",
        "rank": 10,
        "originalEng": "proposal"
      }
    ]
  },
  "FR": {
    "name": "フランス",
    "flag": "🇫🇷",
    "score": 59,
    "trends": [
      {
        "word": "戦争",
        "count": 50975,
        "cat": "geo",
        "trend": "up",
        "rank": 1,
        "originalEng": "war"
      },
      {
        "word": "真ん中",
        "count": 46147,
        "cat": "social",
        "trend": "down",
        "rank": 2,
        "originalEng": "middle"
      },
      {
        "word": "東",
        "count": 43842,
        "cat": "econ",
        "trend": "down",
        "rank": 3,
        "originalEng": "east"
      },
      {
        "word": "not",
        "count": 39529,
        "cat": "social",
        "trend": "down",
        "rank": 4,
        "originalEng": "not"
      },
      {
        "word": "ではありません",
        "count": 34760,
        "cat": "econ",
        "trend": "down",
        "rank": 5,
        "originalEng": "front"
      },
      {
        "word": "フロント",
        "count": 30747,
        "cat": "social",
        "trend": "down",
        "rank": 6,
        "originalEng": "accuses"
      },
      {
        "word": "非難する",
        "count": 26714,
        "cat": "econ",
        "trend": "down",
        "rank": 7,
        "originalEng": "united"
      },
      {
        "word": "団結",
        "count": 22961,
        "cat": "econ",
        "trend": "down",
        "rank": 8,
        "originalEng": "kingdom"
      },
      {
        "word": "王国",
        "count": 19102,
        "cat": "tech",
        "trend": "up",
        "rank": 9,
        "originalEng": "french"
      },
      {
        "word": "フランス語",
        "count": 15431,
        "cat": "social",
        "trend": "down",
        "rank": 10,
        "originalEng": "popular"
      }
    ]
  },
  "AU": {
    "name": "オーストラリア",
    "flag": "🇦🇺",
    "score": 55,
    "trends": [
      {
        "word": "人気",
        "count": 51613,
        "cat": "econ",
        "trend": "down",
        "rank": 1,
        "originalEng": "nation"
      },
      {
        "word": "国家",
        "count": 47231,
        "cat": "tech",
        "trend": "up",
        "rank": 2,
        "originalEng": "australian"
      },
      {
        "word": "オーストラリア",
        "count": 43266,
        "cat": "social",
        "trend": "down",
        "rank": 3,
        "originalEng": "unacceptable"
      },
      {
        "word": "受け入れられない",
        "count": 38575,
        "cat": "tech",
        "trend": "up",
        "rank": 4,
        "originalEng": "bring"
      },
      {
        "word": "持って行きます",
        "count": 35480,
        "cat": "social",
        "trend": "down",
        "rank": 5,
        "originalEng": "home"
      },
      {
        "word": "ホーム",
        "count": 30531,
        "cat": "geo",
        "trend": "up",
        "rank": 6,
        "originalEng": "inside"
      },
      {
        "word": "内側",
        "count": 27670,
        "cat": "geo",
        "trend": "up",
        "rank": 7,
        "originalEng": "queensland"
      },
      {
        "word": "イラン",
        "count": 23798,
        "cat": "tech",
        "trend": "up",
        "rank": 8,
        "originalEng": "iran"
      },
      {
        "word": "クイーンズランド州",
        "count": 18173,
        "cat": "geo",
        "trend": "up",
        "rank": 9,
        "originalEng": "cant"
      },
      {
        "word": "できません",
        "count": 14573,
        "cat": "geo",
        "trend": "up",
        "rank": 10,
        "originalEng": "health"
      }
    ]
  },
  "KR": {
    "name": "韓国",
    "flag": "🇰🇷",
    "score": 74,
    "trends": [
      {
        "word": "イラン",
        "count": 51612,
        "cat": "tech",
        "trend": "up",
        "rank": 1,
        "originalEng": "iran"
      },
      {
        "word": "健康",
        "count": 47516,
        "cat": "tech",
        "trend": "up",
        "rank": 2,
        "originalEng": "park"
      },
      {
        "word": "公園",
        "count": 43780,
        "cat": "geo",
        "trend": "up",
        "rank": 3,
        "originalEng": "second"
      },
      {
        "word": "2 番目",
        "count": 38331,
        "cat": "tech",
        "trend": "up",
        "rank": 4,
        "originalEng": "high"
      },
      {
        "word": "学校",
        "count": 34896,
        "cat": "geo",
        "trend": "up",
        "rank": 5,
        "originalEng": "school"
      },
      {
        "word": "ギフト",
        "count": 30257,
        "cat": "geo",
        "trend": "up",
        "rank": 6,
        "originalEng": "gift"
      },
      {
        "word": "学生",
        "count": 26892,
        "cat": "econ",
        "trend": "down",
        "rank": 7,
        "originalEng": "student"
      },
      {
        "word": "完了",
        "count": 23610,
        "cat": "social",
        "trend": "down",
        "rank": 8,
        "originalEng": "complete"
      },
      {
        "word": "ブク",
        "count": 19381,
        "cat": "tech",
        "trend": "up",
        "rank": 9,
        "originalEng": "bukgu"
      },
      {
        "word": "居住者",
        "count": 15131,
        "cat": "geo",
        "trend": "up",
        "rank": 10,
        "originalEng": "resident"
      }
    ]
  },
  "BR": {
    "name": "ブラジル",
    "flag": "🇧🇷",
    "score": 52,
    "trends": [
      {
        "word": "百万",
        "count": 51327,
        "cat": "geo",
        "trend": "up",
        "rank": 1,
        "originalEng": "million"
      },
      {
        "word": "4",
        "count": 47374,
        "cat": "tech",
        "trend": "up",
        "rank": 2,
        "originalEng": "four"
      },
      {
        "word": "ハンタウイルス",
        "count": 42771,
        "cat": "econ",
        "trend": "down",
        "rank": 3,
        "originalEng": "hantavirus"
      },
      {
        "word": "終わり",
        "count": 38111,
        "cat": "social",
        "trend": "down",
        "rank": 4,
        "originalEng": "end"
      },
      {
        "word": "わかります",
        "count": 35343,
        "cat": "tech",
        "trend": "up",
        "rank": 5,
        "originalEng": "understand"
      },
      {
        "word": "月",
        "count": 30131,
        "cat": "geo",
        "trend": "up",
        "rank": 6,
        "originalEng": "month"
      },
      {
        "word": "ボルソナロ",
        "count": 27781,
        "cat": "econ",
        "trend": "down",
        "rank": 7,
        "originalEng": "bolsonaro"
      },
      {
        "word": "フロント",
        "count": 22164,
        "cat": "social",
        "trend": "down",
        "rank": 8,
        "originalEng": "accuses"
      },
      {
        "word": "発表します",
        "count": 19719,
        "cat": "tech",
        "trend": "up",
        "rank": 9,
        "originalEng": "announces"
      },
      {
        "word": "イラン",
        "count": 15616,
        "cat": "tech",
        "trend": "up",
        "rank": 10,
        "originalEng": "iran"
      }
    ]
  },
  "CA": {
    "name": "カナダ",
    "flag": "🇨🇦",
    "score": 58,
    "trends": [
      {
        "word": "北",
        "count": 50106,
        "cat": "econ",
        "trend": "down",
        "rank": 1,
        "originalEng": "north"
      },
      {
        "word": "カナダ人",
        "count": 46778,
        "cat": "geo",
        "trend": "up",
        "rank": 2,
        "originalEng": "canadians"
      },
      {
        "word": "緊急",
        "count": 43404,
        "cat": "econ",
        "trend": "down",
        "rank": 3,
        "originalEng": "emergency"
      },
      {
        "word": "クラッシュ",
        "count": 38524,
        "cat": "social",
        "trend": "down",
        "rank": 4,
        "originalEng": "crash"
      },
      {
        "word": "だめ",
        "count": 34231,
        "cat": "econ",
        "trend": "down",
        "rank": 5,
        "originalEng": "ont"
      },
      {
        "word": "悪夢",
        "count": 31018,
        "cat": "social",
        "trend": "down",
        "rank": 6,
        "originalEng": "nightmare"
      },
      {
        "word": "カナダ人",
        "count": 26836,
        "cat": "econ",
        "trend": "down",
        "rank": 7,
        "originalEng": "canadian"
      },
      {
        "word": "最高",
        "count": 23627,
        "cat": "geo",
        "trend": "up",
        "rank": 8,
        "originalEng": "best"
      },
      {
        "word": "xcom",
        "count": 19422,
        "cat": "econ",
        "trend": "down",
        "rank": 9,
        "originalEng": "xcom"
      },
      {
        "word": "イラン",
        "count": 14425,
        "cat": "tech",
        "trend": "up",
        "rank": 10,
        "originalEng": "iran"
      }
    ]
  },
  "RU": {
    "name": "ロシア",
    "flag": "🇷🇺",
    "score": 80,
    "trends": [
      {
        "word": "勝利",
        "count": 51227,
        "cat": "tech",
        "trend": "up",
        "rank": 1,
        "originalEng": "victory"
      },
      {
        "word": "called",
        "count": 47589,
        "cat": "social",
        "trend": "down",
        "rank": 2,
        "originalEng": "called"
      },
      {
        "word": "と呼ばれる写真",
        "count": 43827,
        "cat": "tech",
        "trend": "up",
        "rank": 3,
        "originalEng": "photo"
      },
      {
        "word": "ターゲット",
        "count": 39494,
        "cat": "tech",
        "trend": "up",
        "rank": 4,
        "originalEng": "targets"
      },
      {
        "word": "ロシア",
        "count": 34306,
        "cat": "econ",
        "trend": "down",
        "rank": 5,
        "originalEng": "russia"
      },
      {
        "word": "トランプ",
        "count": 30654,
        "cat": "tech",
        "trend": "up",
        "rank": 6,
        "originalEng": "trump"
      },
      {
        "word": "ウラジオストク",
        "count": 27577,
        "cat": "tech",
        "trend": "up",
        "rank": 7,
        "originalEng": "vladivostok"
      },
      {
        "word": "週",
        "count": 22686,
        "cat": "geo",
        "trend": "up",
        "rank": 8,
        "originalEng": "week"
      },
      {
        "word": "会議",
        "count": 19536,
        "cat": "social",
        "trend": "down",
        "rank": 9,
        "originalEng": "meeting"
      },
      {
        "word": "イギリス人",
        "count": 15304,
        "cat": "social",
        "trend": "down",
        "rank": 10,
        "originalEng": "british"
      }
    ]
  },
  "CN": {
    "name": "中国",
    "flag": "🇨🇳",
    "score": 85,
    "trends": [
      {
        "word": "軍隊",
        "count": 51894,
        "cat": "social",
        "trend": "down",
        "rank": 1,
        "originalEng": "military"
      },
      {
        "word": "ホン",
        "count": 46772,
        "cat": "geo",
        "trend": "up",
        "rank": 2,
        "originalEng": "hong"
      },
      {
        "word": "東部",
        "count": 42359,
        "cat": "geo",
        "trend": "up",
        "rank": 3,
        "originalEng": "eastern"
      },
      {
        "word": "発表されました",
        "count": 38277,
        "cat": "social",
        "trend": "down",
        "rank": 4,
        "originalEng": "announced"
      },
      {
        "word": "中国語",
        "count": 35533,
        "cat": "econ",
        "trend": "down",
        "rank": 5,
        "originalEng": "chinese"
      },
      {
        "word": "単位",
        "count": 31896,
        "cat": "social",
        "trend": "down",
        "rank": 6,
        "originalEng": "units"
      },
      {
        "word": "メンズ",
        "count": 26854,
        "cat": "econ",
        "trend": "down",
        "rank": 7,
        "originalEng": "mens"
      },
      {
        "word": "チーム",
        "count": 23573,
        "cat": "econ",
        "trend": "down",
        "rank": 8,
        "originalEng": "team"
      },
      {
        "word": "離れて",
        "count": 19393,
        "cat": "tech",
        "trend": "up",
        "rank": 9,
        "originalEng": "away"
      },
      {
        "word": "トランプ",
        "count": 14351,
        "cat": "tech",
        "trend": "up",
        "rank": 10,
        "originalEng": "trump"
      }
    ]
  }
}